formulapy/__init__.py
formulapy/__release_info__.py
formulapy/api.py
formulapy/cli.py
formulapy/mapping.py
formulapy-0.1.10.dist-info/METADATA
formulapy-0.1.10.dist-info/RECORD
formulapy-0.1.10.dist-info/WHEEL
formulapy-0.1.10.dist-info/entry_points.txt
formulapy-0.1.10.dist-info/top_level.txt
