Metadata-Version: 2.1
Name: formulapy
Version: 0.1.10
Summary: external tools for python to write math formula.
Home-page: https://github.com/thautwarm/formulapy
Author: thautwarm
Author-email: twshere@outlook.com
License: MIT
Keywords: formula,python,math,external tools
Platform: any
Classifier: Programming Language :: Python :: 3.6
Classifier: Programming Language :: Python :: 3.7
Classifier: Programming Language :: Python :: Implementation :: CPython
Requires-Python: >=3.6.0
Requires-Dist: wisepy
Requires-Dist: Redy (>=0.2.6)
